evaluate/__init__.py
evaluate/config.py
evaluate/hub.py
evaluate/info.py
evaluate/inspect.py
evaluate/loading.py
evaluate/module.py
evaluate/naming.py
evaluate/saving.py
evaluate/visualization.py
evaluate/commands/__init__.py
evaluate/commands/evaluate_cli.py
evaluate/evaluation_suite/__init__.py
evaluate/evaluator/__init__.py
evaluate/evaluator/audio_classification.py
evaluate/evaluator/automatic_speech_recognition.py
evaluate/evaluator/base.py
evaluate/evaluator/image_classification.py
evaluate/evaluator/question_answering.py
evaluate/evaluator/text2text_generation.py
evaluate/evaluator/text_classification.py
evaluate/evaluator/text_generation.py
evaluate/evaluator/token_classification.py
evaluate/evaluator/utils.py
evaluate/utils/__init__.py
evaluate/utils/file_utils.py
evaluate/utils/gradio.py
evaluate/utils/logging.py
evaluate-0.4.5.dist-info/LICENSE
evaluate-0.4.5.dist-info/METADATA
evaluate-0.4.5.dist-info/WHEEL
evaluate-0.4.5.dist-info/entry_points.txt
evaluate-0.4.5.dist-info/top_level.txt
evaluate-0.4.5.dist-info/RECORD
