Metadata-Version: 2.1
Name: evaluate
Version: 0.4.5
Summary: HuggingFace community-driven open-source library of evaluation
Home-page: https://github.com/huggingface/evaluate
Author: HuggingFace Inc.
Author-email: leandro@huggingface.co
License: Apache 2.0
Download-URL: https://github.com/huggingface/evaluate/tags
Keywords: metrics machine learning evaluate evaluation
Platform: UNKNOWN
Classifier: Development Status :: 5 - Production/Stable
Classifier: Intended Audience :: Developers
Classifier: Intended Audience :: Education
Classifier: Intended Audience :: Science/Research
Classifier: License :: OSI Approved :: Apache Software License
Classifier: Operating System :: OS Independent
Classifier: Programming Language :: Python :: 3
Classifier: Programming Language :: Python :: 3.8
Classifier: Programming Language :: Python :: 3.9
Classifier: Programming Language :: Python :: 3.10
Classifier: Topic :: Scientific/Engineering :: Artificial Intelligence
Requires-Python: >=3.8.0
Provides-Extra: tensorflow
Provides-Extra: tensorflow_gpu
Provides-Extra: torch
Provides-Extra: dev
Provides-Extra: tests
Provides-Extra: quality
Provides-Extra: docs
Provides-Extra: template
Provides-Extra: evaluator
License-File: LICENSE
